hangman/Words.dat
hangman/__init__.py
hangman/data.py
hangman/efx.py
hangman/game.py
hangman/sides.py
hangman/start.py
G_hangman-1.0.0.dist-info/LICENSE
G_hangman-1.0.0.dist-info/METADATA
G_hangman-1.0.0.dist-info/WHEEL
G_hangman-1.0.0.dist-info/entry_points.txt
G_hangman-1.0.0.dist-info/top_level.txt
G_hangman-1.0.0.dist-info/RECORD
